setup.py
django_reportview.egg-info/PKG-INFO
django_reportview.egg-info/SOURCES.txt
django_reportview.egg-info/dependency_links.txt
django_reportview.egg-info/not-zip-safe
django_reportview.egg-info/requires.txt
django_reportview.egg-info/top_level.txt
reportview/__init__.py
reportview/models.py
reportview/tests.py
reportview/views.py