Metadata-Version: 1.0
Name: django-reportview
Version: 0.1
Summary: Class-based views for PDF output
Home-page: http://dashdrum.com/reportview/
Author: Dan Gentry
Author-email: dan@dashdrum.com
License: NCSA
Keywords: django,views,PDF,RML
Platform: UNKNOWN
Classifier: Framework :: Django
